LICENSE
MANIFEST.in
README.rst
RELEASE-VERSION
setup.py
docs/admin-panel-users.png
docs/app-fwk-plugins.png
docs/appfwk-arch.png
docs/geolocation-admin.png
docs/plugins-popup.png
docs/simple-report.png
docs/stock-criteria.png
docs/stock-widget.png
docs/update-all-reports-popup.png
gitpy_versioning/.git
gitpy_versioning/.gitignore
gitpy_versioning/README.md
gitpy_versioning/__init__.py
gitpy_versioning/__init__.pyc
gitpy_versioning/test_gitpy_versioning.py
steelscript/__init__.py
steelscript.appfwk.egg-info/PKG-INFO
steelscript.appfwk.egg-info/SOURCES.txt
steelscript.appfwk.egg-info/dependency_links.txt
steelscript.appfwk.egg-info/entry_points.txt
steelscript.appfwk.egg-info/namespace_packages.txt
steelscript.appfwk.egg-info/requires.txt
steelscript.appfwk.egg-info/top_level.txt
steelscript/appfwk/__init__.py
steelscript/appfwk/manage.py
steelscript/appfwk/apps/__init__.py
steelscript/appfwk/apps/alerting/__init__.py
steelscript/appfwk/apps/alerting/caches.py
steelscript/appfwk/apps/alerting/datastructures.py
steelscript/appfwk/apps/alerting/models.py
steelscript/appfwk/apps/alerting/serializers.py
steelscript/appfwk/apps/alerting/source.py
steelscript/appfwk/apps/alerting/urls.py
steelscript/appfwk/apps/alerting/views.py
steelscript/appfwk/apps/alerting/management/__init__.py
steelscript/appfwk/apps/alerting/management/commands/__init__.py
steelscript/appfwk/apps/alerting/management/commands/alert.py
steelscript/appfwk/apps/alerting/senders/__init__.py
steelscript/appfwk/apps/alerting/senders/base.py
steelscript/appfwk/apps/alerting/senders/smtp.py
steelscript/appfwk/apps/alerting/senders/snmp.py
steelscript/appfwk/apps/alerting/senders/vm.py
steelscript/appfwk/apps/alerting/tests/__init__.py
steelscript/appfwk/apps/alerting/tests/test_results.py
steelscript/appfwk/apps/datasource/__init__.py
steelscript/appfwk/apps/datasource/admin.py
steelscript/appfwk/apps/datasource/exceptions.py
steelscript/appfwk/apps/datasource/forms.py
steelscript/appfwk/apps/datasource/models.py
steelscript/appfwk/apps/datasource/serializers.py
steelscript/appfwk/apps/datasource/urls.py
steelscript/appfwk/apps/datasource/views.py
steelscript/appfwk/apps/datasource/management/__init__.py
steelscript/appfwk/apps/datasource/management/commands/__init__.py
