Metadata-Version: 2.1
Name: steelscript.appfwk
Version: 1.8
Summary: Core apps for Riverbed SteelScript Application Framework
Home-page: http://pythonhosted.org/steelscript
Author: Riverbed Technology
Author-email: eng-github@riverbed.com
License: MIT
Platform: Linux
Platform: Mac OS
Platform: Windows
Classifier: Development Status :: 4 - Beta
Classifier: Framework :: Django
Classifier: Intended Audience :: Developers
Classifier: Intended Audience :: Information Technology
Classifier: Intended Audience :: System Administrators
Classifier: License :: OSI Approved :: MIT License
Classifier: Operating System :: OS Independent
Classifier: Programming Language :: Python :: 2.7
Classifier: Topic :: System :: Networking
Classifier: Topic :: Software Development
Provides-Extra: test
Provides-Extra: doc
Provides-Extra: all
Provides-Extra: dev
